wakatime_client/__init__.py
wakatime_client/py.typed
wakatime_client-0.3.1.dist-info/METADATA
wakatime_client-0.3.1.dist-info/WHEEL
wakatime_client-0.3.1.dist-info/licenses/LICENSE
wakatime_client-0.3.1.dist-info/RECORD
